odoo8_addon_project_billing_utils-8.0.1.4.0.99.dev5-py2.7-nspkg.pth
odoo8_addon_project_billing_utils-8.0.1.4.0.99.dev5.dist-info/METADATA
odoo8_addon_project_billing_utils-8.0.1.4.0.99.dev5.dist-info/RECORD
odoo8_addon_project_billing_utils-8.0.1.4.0.99.dev5.dist-info/WHEEL
odoo8_addon_project_billing_utils-8.0.1.4.0.99.dev5.dist-info/namespace_packages.txt
odoo8_addon_project_billing_utils-8.0.1.4.0.99.dev5.dist-info/top_level.txt
odoo_addons/project_billing_utils/README.rst
odoo_addons/project_billing_utils/__init__.py
odoo_addons/project_billing_utils/__openerp__.py
odoo_addons/project_billing_utils/analytic.py
odoo_addons/project_billing_utils/invoice.py
odoo_addons/project_billing_utils/invoice_view.xml
odoo_addons/project_billing_utils/project.py
odoo_addons/project_billing_utils/project_view.xml
odoo_addons/project_billing_utils/static/description/icon.png
odoo_addons/project_billing_utils/wizard/__init__.py
odoo_addons/project_billing_utils/wizard/associate_aal.py
odoo_addons/project_billing_utils/wizard/associate_aal_view.xml
odoo_addons/project_billing_utils/wizard/blank_invoice.py
odoo_addons/project_billing_utils/wizard/blank_invoice_view.xml
odoo_addons/project_billing_utils/wizard/dissociate_aal.py
odoo_addons/project_billing_utils/wizard/dissociate_aal_view.xml
odoo_addons/project_billing_utils/wizard/open_invoices.py
odoo_addons/project_billing_utils/wizard/open_invoices_view.xml
