Metadata-Version: 2.1
Name: odoo8-addon-project-billing-utils
Version: 8.0.1.4.0.99.dev5
Summary: Analytic and project wizard for service companies
Home-page: http://www.camptocamp.com
Author: Camptocamp,Odoo Community Association (OCA)
Author-email: support@odoo-community.org
License: UNKNOWN
Platform: UNKNOWN
Classifier: Programming Language :: Python
Classifier: Framework :: Odoo
Requires-Python: ~=2.7
Requires-Dist: odoo8-addon-project-analytic-line-view
Requires-Dist: odoo (<9.0a,>=8.0a)
